glow_sdk/__init__.py
glow_sdk/models.py
glow_sdk/sdk.py
glow_sdk-0.5.0.dist-info/METADATA
glow_sdk-0.5.0.dist-info/WHEEL
glow_sdk-0.5.0.dist-info/RECORD
